DLstorm/Model.py
DLstorm/VERSION
DLstorm/__init__.py
DLstorm/logger.py
DLstorm/Layers/Base.py
DLstorm/Layers/BatchNormalization.py
DLstorm/Layers/Conv.py
DLstorm/Layers/Dropout.py
DLstorm/Layers/Flatten.py
DLstorm/Layers/FullyConnected.py
DLstorm/Layers/Helpers.py
DLstorm/Layers/Initializers.py
DLstorm/Layers/Pooling.py
DLstorm/Layers/ReLU.py
DLstorm/Layers/SoftMax.py
DLstorm/Layers/__init__.py
DLstorm/Optimization/Loss.py
DLstorm/Optimization/Optimizers.py
DLstorm/Optimization/__init__.py
DLstorm-1.0.2.dist-info/LICENSE
DLstorm-1.0.2.dist-info/METADATA
DLstorm-1.0.2.dist-info/WHEEL
DLstorm-1.0.2.dist-info/top_level.txt
DLstorm-1.0.2.dist-info/RECORD
